calculator_matrix-1.1.dist-info/licenses/LICENSE
matrix_calculator/__init__.py
matrix_calculator/matrix.py
calculator_matrix-1.1.dist-info/METADATA
calculator_matrix-1.1.dist-info/WHEEL
calculator_matrix-1.1.dist-info/top_level.txt
calculator_matrix-1.1.dist-info/RECORD
