Metadata-Version: 2.4
Name: Calculator_matrix
Version: 1.1
License-File: LICENSE
Requires-Dist: numpy
Dynamic: description
Dynamic: license-file
Dynamic: requires-dist
